opencopilot_utils/__init__.py
opencopilot_utils/config.py
opencopilot_utils/embedding_type.py
opencopilot_utils/get_embeddings.py
opencopilot_utils/get_llm.py
opencopilot_utils/get_shared_filepath.py
opencopilot_utils/get_vector_store.py
opencopilot_utils/init_vector_store.py
opencopilot_utils/interfaces.py
opencopilot_utils/store_type.py
opencopilot_utils-2.1.2.dist-info/METADATA
opencopilot_utils-2.1.2.dist-info/WHEEL
opencopilot_utils-2.1.2.dist-info/top_level.txt
opencopilot_utils-2.1.2.dist-info/RECORD
