Metadata-Version: 2.1
Name: opencopilot-utils
Version: 2.1.2
Summary: Utility function for getting embeddings, llms, chat completion models etc
Requires-Dist: langchain
